src/whisper_ctranslate2/commandline.py
src/whisper_ctranslate2/diarization.py
src/whisper_ctranslate2/languages.py
src/whisper_ctranslate2/live.py
src/whisper_ctranslate2/transcribe.py
src/whisper_ctranslate2/version.py
src/whisper_ctranslate2/whisper_ctranslate2.py
src/whisper_ctranslate2/writers.py
whisper_ctranslate2_remote_api-0.4.5.dist-info/LICENSE
whisper_ctranslate2_remote_api-0.4.5.dist-info/METADATA
whisper_ctranslate2_remote_api-0.4.5.dist-info/WHEEL
whisper_ctranslate2_remote_api-0.4.5.dist-info/entry_points.txt
whisper_ctranslate2_remote_api-0.4.5.dist-info/top_level.txt
whisper_ctranslate2_remote_api-0.4.5.dist-info/RECORD
