Metadata-Version: 2.1
Name: whisper-ctranslate2-remote-api
Version: 0.4.5
Summary: Whisper command line client that uses a remote CTranslate2/faster-whisper instance via a remote API call
Home-page: https://github.com/rkilchmn/whisper-ctranslate2-remote-api
Author: Jordi Mas, Roger Kilchenmann
Author-email: jmas@softcatala.org
License: MIT
Platform: UNKNOWN
Classifier: License :: OSI Approved :: MIT License
Classifier: Programming Language :: Python :: 3.6
Classifier: Programming Language :: Python :: 3.7
Classifier: Programming Language :: Python :: 3.8
Classifier: Programming Language :: Python :: 3.9
Classifier: Programming Language :: Python :: 3.10
Classifier: Programming Language :: Python :: 3.11
Classifier: Programming Language :: Python :: 3.12
Classifier: Topic :: Scientific/Engineering :: Artificial Intelligence
License-File: LICENSE
Requires-Dist: ctranslate2
Requires-Dist: faster-whisper>=1.0.2
Requires-Dist: faster-whisper-api-proxy
Requires-Dist: libparse
Requires-Dist: numpy
Requires-Dist: sounddevice
Requires-Dist: tqdm
Provides-Extra: dev
Requires-Dist: black==24.*; extra == "dev"
Requires-Dist: flake8==7.*; extra == "dev"
Requires-Dist: nose2; extra == "dev"
